topsis_tavish_102303246/__init__.py
topsis_tavish_102303246-0.1.1.dist-info/WHEEL
topsis_tavish_102303246-0.1.1.dist-info/entry_points.txt
topsis_tavish_102303246-0.1.1.dist-info/METADATA
topsis_tavish_102303246-0.1.1.dist-info/RECORD
