Metadata-Version: 2.3
Name: topsis-tavish-102303246
Version: 0.1.1
Summary: A Python package for Topsis method implementation
Author: Tavish Sood
Author-email: Tavish Sood <tavish005sood@gmail.com>
Requires-Dist: argparse>=1.4.0
Requires-Dist: pandas>=2.3.3
Requires-Dist: pyxlsx>=1.1.3
Requires-Python: >=3.11
